setup.py
akshita_distributions_2306/Binomialdistribution.py
akshita_distributions_2306/Gaussiandistribution.py
akshita_distributions_2306/Generaldistribution.py
akshita_distributions_2306/__init__.py
akshita_distributions_2306.egg-info/PKG-INFO
akshita_distributions_2306.egg-info/SOURCES.txt
akshita_distributions_2306.egg-info/dependency_links.txt
akshita_distributions_2306.egg-info/not-zip-safe
akshita_distributions_2306.egg-info/top_level.txt