Metadata-Version: 1.0
Name: akshita-distributions-2306
Version: 2.2
Summary: Gaussian distributions
Home-page: UNKNOWN
Author: UNKNOWN
Author-email: UNKNOWN
License: UNKNOWN
Platform: UNKNOWN
